bareasgi_auth_common/__init__.py
bareasgi_auth_common/helpers.py
bareasgi_auth_common/http_jwt_authenticator.py
bareasgi_auth_common/py.typed
bareasgi_auth_common/token_manager.py
bareasgi_auth_common/types.py
bareasgi_auth_common/utils.py
bareasgi_auth_common/websocket_jwt_authenticator.py
bareasgi_auth_common-4.1.1.dist-info/LICENSE
bareasgi_auth_common-4.1.1.dist-info/WHEEL
bareasgi_auth_common-4.1.1.dist-info/METADATA
bareasgi_auth_common-4.1.1.dist-info/RECORD
